LICENSE
MANIFEST.in
README.md
requirements.txt
setup.py
pyhmmsearch/__init__.py
pyhmmsearch/pyhmmsearch.py
pyhmmsearch/reformat_pyhmmsearch.py
pyhmmsearch/serialize_hmm_models.py
pyhmmsearch.egg-info/PKG-INFO
pyhmmsearch.egg-info/SOURCES.txt
pyhmmsearch.egg-info/dependency_links.txt
pyhmmsearch.egg-info/entry_points.txt
pyhmmsearch.egg-info/requires.txt
pyhmmsearch.egg-info/top_level.txt